[
  {
    "type": "bottom",
    "side": [
      "Usec"
    ],
    "suiteId": "6658a01e3733207cb6677dc7",
    "outfitId": "623b19160671474197ab1ff2",
    "bottomId": "642c19360a69698d1b049e12",
    "locales": {
      "en": {
        "name": "USEC Practical",
        "description": "Combat pants"
      }
    },
    "bottomBundlePath": "assets/content/characters/character/prefabs/pants_bt_1.bundle",
    "traderId": "6617beeaa9cfa777ca915b7c",
    "loyaltyLevel": 3,
    "profileLevel": 30,
    "standing": 0,
    "currencyId": "6656560053eaaa7a23349c86",
    "price": 6,
    "questRequirements": [],
    "achievementRequirements": []
  },
  {
    "type": "bottom",
    "side": [
      "Usec"
    ],
    "suiteId": "6658a1d54de4820934746dd4",
    "outfitId": "dc44a96a767f46b7a71dd7a6",
    "bottomId": "642d6941ff5ecad7810a8a61",
    "locales": {
      "en": {
        "name": "USEC Lowland Green",
        "description": "Combat pants"
      }
    },
    "bottomBundlePath": "assets/content/characters/character/prefabs/pants_bt_3.bundle",
    "traderId": "6617beeaa9cfa777ca915b7c",
    "loyaltyLevel": 4,
    "profileLevel": 42,
    "standing": 0,
    "currencyId": "6656560053eaaa7a23349c86",
    "price": 10,
    "questRequirements": [],
    "achievementRequirements": []
  }
]
